mickey_utils/__init__.py
mickey_utils/my_utils.py
mickey_utils-0.0.6.data/data/requirements.txt
mickey_utils-0.0.6.dist-info/LICENSE
mickey_utils-0.0.6.dist-info/METADATA
mickey_utils-0.0.6.dist-info/WHEEL
mickey_utils-0.0.6.dist-info/top_level.txt
mickey_utils-0.0.6.dist-info/RECORD
