Metadata-Version: 2.1
Name: mickey-utils
Version: 0.0.6
Summary: 个人日常工作工具集
Author: fanghoujun
Author-email: fanghoujun@126.com
Classifier: Programming Language :: Python :: 3
Classifier: License :: OSI Approved :: MIT License
Classifier: Operating System :: OS Independent
Requires-Python: >=3.8
License-File: LICENSE
Requires-Dist: Requests ==2.32.3
